{
	"name": "Layout 1",
	"layers": [
		{
			"name": "Layer 0",
			"overriden": 0,
			"instances": [
				{
					"type": "9patch",
					"properties": {
						"left-margin": 16,
						"right-margin": 16,
						"top-margin": 16,
						"bottom-margin": 16,
						"edges": "stretch",
						"fill": "stretch",
						"initially-visible": true,
						"origin": "top-left",
						"seams": "overlap"
					},
					"uid": 4,
					"instanceVariables": {},
					"behaviors": {},
					"world": {
						"x": 2,
						"y": 2,
						"width": 1707,
						"height": 960,
						"originX": 0,
						"originY": 0,
						"color": [
							1,
							1,
							1,
							1
						],
						"angle": 0,
						"zElevation": 0
					}
				},
				{
					"type": "platform",
					"properties": {
						"initially-visible": true,
						"initial-animation": "Animation 1",
						"initial-frame": 0,
						"enable-collisions": true,
						"live-preview": false
					},
					"uid": 2,
					"instanceVariables": {},
					"behaviors": {
						"Solid": {
							"properties": {
								"enabled": true,
								"tags": ""
							}
						},
						"Physics": {
							"properties": {
								"immovable": true,
								"collision-mask": "bounding-box",
								"prevent-rotation": false,
								"density": 1,
								"friction": 0.5,
								"elasticity": 0.2,
								"linear-damping": 0,
								"angular-damping": 0.01,
								"bullet": false,
								"enabled": true
							}
						}
					},
					"world": {
						"x": 857,
						"y": 597,
						"width": 1707,
						"height": 250,
						"originX": 0.5,
						"originY": 0.5,
						"color": [
							1,
							1,
							1,
							1
						],
						"angle": 0,
						"zElevation": 0
					}
				},
				{
					"type": "bones",
					"properties": {
						"initially-visible": true,
						"initial-animation": "Animation 1",
						"initial-frame": 0,
						"enable-collisions": true,
						"live-preview": false
					},
					"uid": 3,
					"instanceVariables": {},
					"behaviors": {
						"Platform": {
							"properties": {
								"max-speed": 330,
								"acceleration": 1500,
								"deceleration": 1500,
								"jump-strength": 650,
								"gravity": 1500,
								"max-fall-speed": 1000,
								"double-jump": false,
								"jump-sustain": 0,
								"default-controls": true,
								"enabled": true
							}
						},
						"ScrollTo": {
							"properties": {
								"enabled": true
							}
						}
					},
					"world": {
						"x": 724,
						"y": 346,
						"width": 71,
						"height": 74,
						"originX": 0.5094339622641509,
						"originY": 0.5374149659863946,
						"color": [
							1,
							1,
							1,
							1
						],
						"angle": 0,
						"zElevation": 0
					}
				},
				{
					"type": "fist",
					"properties": {
						"initially-visible": true,
						"initial-animation": "Animation 1",
						"initial-frame": 0,
						"enable-collisions": true,
						"live-preview": false
					},
					"uid": 5,
					"instanceVariables": {
						"fists": 1
					},
					"behaviors": {
						"Physics": {
							"properties": {
								"immovable": false,
								"collision-mask": "use-collision-polygon",
								"prevent-rotation": false,
								"density": 1,
								"friction": 0.5,
								"elasticity": 0.2,
								"linear-damping": 0,
								"angular-damping": 0.01,
								"bullet": false,
								"enabled": true
							}
						},
						"Solid": {
							"properties": {
								"enabled": false,
								"tags": ""
							}
						},
						"DestroyOutsideLayout": {
							"properties": {}
						}
					},
					"world": {
						"x": 863.128,
						"y": -62.70786516853933,
						"width": 42,
						"height": 37,
						"originX": 0.384,
						"originY": 0.4943820224719101,
						"color": [
							1,
							1,
							1,
							1
						],
						"angle": 0,
						"zElevation": 0
					}
				},
				{
					"type": "pickupbox",
					"properties": {
						"initially-visible": true,
						"initial-animation": "Animation 1",
						"initial-frame": 0,
						"enable-collisions": true,
						"live-preview": false
					},
					"uid": 7,
					"instanceVariables": {},
					"behaviors": {
						"Pin": {
							"properties": {
								"destroy": false
							}
						}
					},
					"world": {
						"x": 724,
						"y": 341,
						"width": 98,
						"height": 90,
						"originX": 0.5,
						"originY": 0.5,
						"color": [
							1,
							1,
							1,
							1
						],
						"angle": 0,
						"zElevation": 0
					}
				},
				{
					"type": "fistkiller",
					"properties": {
						"initially-visible": true,
						"initial-animation": "Animation 1",
						"initial-frame": 0,
						"enable-collisions": true,
						"live-preview": false
					},
					"uid": 8,
					"instanceVariables": {},
					"behaviors": {},
					"world": {
						"x": 1163,
						"y": 413,
						"width": 54,
						"height": 120,
						"originX": 0.5,
						"originY": 0.5,
						"color": [
							1,
							1,
							1,
							1
						],
						"angle": 0,
						"zElevation": 0
					}
				}
			],
			"sid": 109279290430008,
			"effectTypes": [],
			"isInitiallyVisible": true,
			"color": [
				1,
				1,
				1,
				1
			],
			"backgroundColor": [
				1,
				1,
				1,
				1
			],
			"isTransparent": false,
			"parallaxX": 1,
			"parallaxY": 1,
			"scaleRate": 1,
			"forceOwnTexture": false,
			"useRenderCells": false,
			"blendMode": "normal",
			"global": false
		}
	],
	"sid": 118328827433706,
	"nonworld-instances": [],
	"effectTypes": [],
	"width": 1708,
	"height": 960,
	"unboundedScrolling": false,
	"eventSheet": "Event sheet 1"
}